tls/__init__.py
tls/messaging/__init__.py
tls/messaging/bnum.py
tls/messaging/exceptions.py
tls/messaging/oauth.py
tls/messaging/sms.py
tls/messaging/subscription.py
tls/messaging/types.py
tls/messaging/utils/__init__.py
tls/messaging/utils/config.py
tls/messaging/utils/notify_url.py
tls/messaging/utils/phone_number.py
tls.messaging-0.6.4.dist-info/LICENSE
tls.messaging-0.6.4.dist-info/WHEEL
tls.messaging-0.6.4.dist-info/METADATA
tls.messaging-0.6.4.dist-info/RECORD
