Metadata-Version: 2.1
Name: tls.messaging
Version: 0.6.4
Summary: SDK for the Telstra Messaging API
License: Apache-2.0
Author: David Andersson
Author-email: david-andersson@users.noreply.github.com 
Requires-Python: >=3.6,<4.0
Classifier: License :: OSI Approved :: Apache Software License
Classifier: Programming Language :: Python :: 3
Classifier: Programming Language :: Python :: 3.6
Classifier: Programming Language :: Python :: 3.7
Classifier: Programming Language :: Python :: 3.8
Classifier: Programming Language :: Python :: 3.9
